pathman/__init__.py
pathman/base.py
pathman/copy.py
pathman/exc.py
pathman/path.py
pathman/py.typed
pathman/utils.py
pathman/_impl/__init__.py
pathman/_impl/local.py
pathman/_impl/s3.py
tests/output/__init__.py
tests/resources/__init__.py
pathman-0.2.3.dist-info/LICENSE
pathman-0.2.3.dist-info/METADATA
pathman-0.2.3.dist-info/WHEEL
pathman-0.2.3.dist-info/top_level.txt
pathman-0.2.3.dist-info/RECORD
