Metadata-Version: 2.1
Name: pathman
Version: 0.2.3
Summary: Utility for interacting with local and remote paths through a uniform interface
Home-page: UNKNOWN
Author: Blackfynn, Inc.
Author-email: zach.duey@blackfynn.com
License: UNKNOWN
Platform: UNKNOWN
Classifier: Development Status :: 3 - Alpha
Classifier: Topic :: Utilities
